yinming_maxcompute_mcp_server/__init__.py
yinming_maxcompute_mcp_server-0.1.6.dist-info/METADATA
yinming_maxcompute_mcp_server-0.1.6.dist-info/WHEEL
yinming_maxcompute_mcp_server-0.1.6.dist-info/entry_points.txt
yinming_maxcompute_mcp_server-0.1.6.dist-info/RECORD
